VsCodeZhongwenWendang/README.md
VsCodeZhongwenWendang/__init__.py
VsCodeZhongwenWendang/__main__.py
VsCodeZhongwenWendang/file.epub
VsCodeZhongwenWendang/index.html
VsCodeZhongwenWendang/css/__init__.py
VsCodeZhongwenWendang/css/annotations.css
VsCodeZhongwenWendang/css/main.css
VsCodeZhongwenWendang/css/normalize.css
VsCodeZhongwenWendang/css/popup.css
VsCodeZhongwenWendang/font/__init__.py
VsCodeZhongwenWendang/font/fontello.eot
VsCodeZhongwenWendang/font/fontello.svg
VsCodeZhongwenWendang/font/fontello.ttf
VsCodeZhongwenWendang/font/fontello.woff
VsCodeZhongwenWendang/img/__init__.py
VsCodeZhongwenWendang/img/annotator-glyph-sprite.png
VsCodeZhongwenWendang/img/annotator-icon-sprite.png
VsCodeZhongwenWendang/img/apple-touch-icon.png
VsCodeZhongwenWendang/img/cancelfullscreen.png
VsCodeZhongwenWendang/img/close.png
VsCodeZhongwenWendang/img/fullscreen.png
VsCodeZhongwenWendang/img/loader.gif
VsCodeZhongwenWendang/img/menu-icon.png
VsCodeZhongwenWendang/img/save.png
VsCodeZhongwenWendang/img/saved.png
VsCodeZhongwenWendang/img/settings-s.png
VsCodeZhongwenWendang/img/settings.png
VsCodeZhongwenWendang/img/star.png
VsCodeZhongwenWendang/js/__init__.py
VsCodeZhongwenWendang/js/epub.js
VsCodeZhongwenWendang/js/epub.min.js
VsCodeZhongwenWendang/js/epub.min.map
VsCodeZhongwenWendang/js/hooks.min.js
VsCodeZhongwenWendang/js/hooks.min.map
VsCodeZhongwenWendang/js/reader.js
VsCodeZhongwenWendang/js/reader.js.map
VsCodeZhongwenWendang/js/reader.min.js
VsCodeZhongwenWendang/js/reader.min.map
VsCodeZhongwenWendang/js/hooks/__init__.py
VsCodeZhongwenWendang/js/hooks/extensions/__init__.py
VsCodeZhongwenWendang/js/hooks/extensions/highlight.js
VsCodeZhongwenWendang/js/libs/__init__.py
VsCodeZhongwenWendang/js/libs/jquery.min.js
VsCodeZhongwenWendang/js/libs/localforage.min.js
VsCodeZhongwenWendang/js/libs/screenfull.js
VsCodeZhongwenWendang/js/libs/screenfull.min.js
VsCodeZhongwenWendang/js/libs/zip.min.js
VsCodeZhongwenWendang/js/plugins/__init__.py
vs_code_zhongwen_wendang-2024.3.4.0.dist-info/METADATA
vs_code_zhongwen_wendang-2024.3.4.0.dist-info/WHEEL
vs_code_zhongwen_wendang-2024.3.4.0.dist-info/entry_points.txt
vs_code_zhongwen_wendang-2024.3.4.0.dist-info/top_level.txt
vs_code_zhongwen_wendang-2024.3.4.0.dist-info/RECORD
